odoo10_addon_mass_mailing_custom_unsubscribe-10.0.2.0.1-py3.8-nspkg.pth
odoo/addons/mass_mailing_custom_unsubscribe/README.rst
odoo/addons/mass_mailing_custom_unsubscribe/__init__.py
odoo/addons/mass_mailing_custom_unsubscribe/__manifest__.py
odoo/addons/mass_mailing_custom_unsubscribe/exceptions.py
odoo/addons/mass_mailing_custom_unsubscribe/controllers/__init__.py
odoo/addons/mass_mailing_custom_unsubscribe/controllers/main.py
odoo/addons/mass_mailing_custom_unsubscribe/data/mail_unsubscription_reason.xml
odoo/addons/mass_mailing_custom_unsubscribe/demo/assets.xml
odoo/addons/mass_mailing_custom_unsubscribe/i18n/am.po
odoo/addons/mass_mailing_custom_unsubscribe/i18n/ar.po
odoo/addons/mass_mailing_custom_unsubscribe/i18n/bg.po
odoo/addons/mass_mailing_custom_unsubscribe/i18n/bs.po
odoo/addons/mass_mailing_custom_unsubscribe/i18n/ca.po
odoo/addons/mass_mailing_custom_unsubscribe/i18n/cs.po
odoo/addons/mass_mailing_custom_unsubscribe/i18n/da.po
odoo/addons/mass_mailing_custom_unsubscribe/i18n/de.po
odoo/addons/mass_mailing_custom_unsubscribe/i18n/el_GR.po
odoo/addons/mass_mailing_custom_unsubscribe/i18n/en_GB.po
odoo/addons/mass_mailing_custom_unsubscribe/i18n/es.po
odoo/addons/mass_mailing_custom_unsubscribe/i18n/es_AR.po
odoo/addons/mass_mailing_custom_unsubscribe/i18n/es_CL.po
odoo/addons/mass_mailing_custom_unsubscribe/i18n/es_CO.po
odoo/addons/mass_mailing_custom_unsubscribe/i18n/es_CR.po
odoo/addons/mass_mailing_custom_unsubscribe/i18n/es_DO.po
odoo/addons/mass_mailing_custom_unsubscribe/i18n/es_EC.po
odoo/addons/mass_mailing_custom_unsubscribe/i18n/es_ES.po
odoo/addons/mass_mailing_custom_unsubscribe/i18n/es_MX.po
odoo/addons/mass_mailing_custom_unsubscribe/i18n/es_PE.po
odoo/addons/mass_mailing_custom_unsubscribe/i18n/es_PY.po
odoo/addons/mass_mailing_custom_unsubscribe/i18n/es_VE.po
odoo/addons/mass_mailing_custom_unsubscribe/i18n/et.po
odoo/addons/mass_mailing_custom_unsubscribe/i18n/eu.po
odoo/addons/mass_mailing_custom_unsubscribe/i18n/fa.po
odoo10_addon_mass_mailing_custom_unsubscribe-10.0.2.0.1.dist-info/METADATA
odoo10_addon_mass_mailing_custom_unsubscribe-10.0.2.0.1.dist-info/WHEEL
odoo10_addon_mass_mailing_custom_unsubscribe-10.0.2.0.1.dist-info/namespace_packages.txt
odoo10_addon_mass_mailing_custom_unsubscribe-10.0.2.0.1.dist-info/top_level.txt
odoo10_addon_mass_mailing_custom_unsubscribe-10.0.2.0.1.dist-info/RECORD
